Workbook

Sheet 📋 Campaign Overview
A1: 🎯 AMAZON DSP — FULL-FUNNEL MEDIA PLAN
A2: Campaign Overview & Strategy | Executive Summary
A5: CAMPAIGN DETAILS
A6: Advertiser / Brand | B6: DAIKEN Biomedical
A7: Campaign Name | B7: 2026 Japan DSP Full-Funnel (Awareness Focus)
A8: Total Budget | B8: ¥5,500,000
A9: Campaign Flight (Dates) | B9: 01/01/2026 – 12/31/2026
A10: Primary Campaign Goal | B10: Drive Awareness / Maximize Reach & Frequency
A11: Promoted Categories/ASINs | B11: Nattokinase, Maca, Fish Oil, Kids Fish Oil, Bitter Melon, Lutein, Multivitamin
A12: Planning Tools Used | B12: Amazon Ads Planner | Channel Planner | Amazon Marketing Cloud (AMC)
A14: FULL-FUNNEL STRATEGY OVERVIEW
A15: Order (Goal) | B15: Funnel Stage | C15: Line Items Included | D15: Key Formats | E15: Budget Allocation
A16: 🚀 1. Prospecting (Growth) | B16: Awareness + Consideration | C16: AMC Lookalikes, In-Market, Brand Halo | D16: STV / OLV / Display | E16: 39% → ¥2,145,000
A17: 🎯 2. Remarketing (The Closer) | B17: Conversion (BOF) | C17: 7-Day PDP Viewers, Cart Abandoners, Conquesting | D17: REC / Display (Static) | E17: 39% → ¥2,145,000
A18: 🔁 3. Loyalty (LTV) | B18: Retention | C18: Repeat Purchase (45-day), SnS Targets, Lapse Prevention | D18: Display / Audio | E18: 22% → ¥1,210,000
A19: TOTAL | 3 Orders | 9 Line Items | E19: 100% → ¥5,500,000
A20: Note: DAA Media Plan categorizes all DSP (¥5,500,000) as Awareness. Full-funnel structure retained for DSP execution.

Sheet 📊 Media Plan
A1: 📊 AMAZON DSP — DETAILED MEDIA PLAN (DAIKEN Biomedical JP — Full-Funnel Blueprint)
A3: SECTION A | STRATEGY & FUNNEL + SECTION B | AUDIENCE & TARGETING + SECTION C | INVENTORY, CREATIVE & FORMATS + SECTION D | BUDGETING & FORECASTING
A4: # | B4: Order (Goal) | C4: Line Item (Targeting) | D4: Objective | E4: Primary KPI | F4: Secondary KPI | G4: Audience Logic | H4: Audience Type | I4: Geo & Device | J4: Media Mix / Inventory | K4: Creative Format | L4: Creative Strategy | M4: Flight Dates | N4: Budget (¥) | O4: Budget % | P4: Est. CPM (¥) | Q4: Est. Impressions
A5: 1 | B5: 1. Prospecting (Growth) 🚀 | C5: AMC Lookalikes | D5: Maximize Reach & Frequency | E5: Reach / VCR | F5: Video Completion Rate | G5: Finds new shoppers whose behavior matches your top 10% buyers (AMC-modelled seed from DAIKEN purchase history). | H5: Lookalike (AMC-Modelled) | I5: Japan / CTV & Mobile | J5: Prime Video, Amazon.co.jp (Amazon O&O) | K5: STV / OLV | L5: Video / Static: Focus on Japanese wellness heritage and natural supplement quality. | M5: 01/01/2026 – 12/31/2026 | N5: 1103143 | O5: =N5/N14 | P5: 3300 | Q5: =(N5/P5)*1000
A6: 2 | B6: ↳ 1 | C6: In-Market Segments | D6: Drive Detail Page Views (DPVR) | E6: DPVR | F6: CTR | G6: Targets users currently browsing "Health Supplements" & "Vitamins" categories on Amazon.co.jp — high intent signals. | H6: In-Market (Category Intent) | I6: Japan / Mobile & Desktop | J6: Amazon.co.jp O&O + Open Web (JP) | K6: Display + OLV | L6: Static: Highlighting product purity and key supplement benefits. | M6: 01/01/2026 – 12/31/2026 | N6: 551571 | O6: =N6/N14 | P6: 1500 | Q6: =(N6/P6)*1000
A7: 3 | B7: ↳ 1 | C7: Brand Halo / Cross-Brand | D7: Drive Category Awareness | E7: Reach / Frequency | F7: DPVR | G7: Targets shoppers of related wellness categories (e.g., Nattokinase, Omega-3, Multivitamin adjacent categories). | H7: Contextual / Category Halo | I7: Japan / Mobile & Desktop | J7: Amazon.co.jp O&O + 3P Open Web (JP) | K7: Display | L7: Static: Promoting DAIKEN as a trusted total wellness brand. | M7: 01/01/2026 – 12/31/2026 | N7: 490286 | O7: =N7/N14 | P7: 1200 | Q7: =(N7/P7)*1000
A8: 4 | B8: 2. Remarketing (The Closer) 🎯 | C8: 7-Day View Remarketing | D8: Drive Purchases (Retargeting) | E8: ROAS | F8: CPP | G8: Re-engages users who viewed your ASINs in the last 7 days but didn't buy. | H8: Remarketing – PDP Viewers (7-day) | I8: Japan / Cross-device | J8: Amazon.co.jp O&O + Open Web (JP) | K8: REC (Responsive eCommerce) | L8: REC: Dynamic ads showing real-time price & star rating. | M8: 01/01/2026 – 12/31/2026 | N8: 980571 | O8: =N8/N14 | P8: 1200 | Q8: =(N8/P8)*1000
A9: 5 | B9: ↳ 2 | C9: AMC Cart Abandoners | D9: Recover Abandoned Carts | E9: CPP | F9: ROAS | G9: High-precision targeting of users who added to cart but left — built via AMC SQL. | H9: Remarketing – Cart Abandon (AMC) | I9: Japan / Cross-device | J9: Amazon.co.jp O&O | K9: REC (Responsive eCommerce) | L9: REC: Including a "Limited Time" coupon if available. | M9: 01/01/2026 – 12/31/2026 | N9: 612857 | O9: =N9/N14 | P9: 1350 | Q9: =(N9/P9)*1000
A10: 6 | B10: ↳ 2 | C10: Competitor Conquesting | D10: Win Competitor Shoppers (NTB) | E10: NTB Purchase Rate | F10: DPVR | G10: Targets shoppers who viewed top competitor supplement products recently — NTB opportunity. | H10: Conquesting – Competitor ASIN Viewers | I10: Japan / Mobile & Desktop | J10: Amazon.co.jp O&O + Open Web (JP) | K10: Display (Static) | L10: Static: A "Why Choose DAIKEN?" comparison chart highlighting differentiators. | M10: 01/01/2026 – 12/31/2026 | N10: 551571 | O10: =N10/N14 | P10: 1425 | Q10: =(N10/P10)*1000
A11: 7 | B11: 3. Loyalty (LTV) 🔁 | C11: Repeat Purchase | D11: Drive Repeat Purchases | E11: ROAS | F11: Purchase Rate | G11: Re-targets past buyers at the 45-day mark to remind them to restock before they churn. | H11: Remarketing – Past Buyers (45-day) | I11: Japan / Cross-device | J11: Amazon.co.jp O&O + Amazon Music JP | K11: Display + Audio | L11: Static: "Time to Refill?" messaging with product + days-since-purchase hook. | M11: 01/01/2026 – 12/31/2026 | N11: 423500 | O11: =N11/N14 | P11: 1500 | Q11: =(N11/P11)*1000
A12: 8 | B12: ↳ 3 | C12: Subscribe & Save (SnS) | D12: Convert to Subscribe & Save | E12: SnS Conversion Rate | F12: CPP | G12: Targets frequent buyers who haven't yet committed to a subscription — high-LTV conversion. | H12: Remarketing – Frequent Buyers (Non-Sub) | I12: Japan / Cross-device | J12: Amazon.co.jp O&O | K12: Display (Static) | L12: Static: Highlighting the % discount for SnS + auto-delivery convenience. | M12: 01/01/2026 – 12/31/2026 | N12: 484000 | O12: =N12/N14 | P12: 1350 | Q12: =(N12/P12)*1000
A13: 9 | B13: ↳ 3 | C13: Lapse Prevention | D13: Win-Back Lapsed Buyers | E13: Re-purchase Rate | F13: CPP | G13: Win-back campaign for buyers who haven't purchased in 6+ months. | H13: Remarketing – Lapsed (6-month+) | I13: Japan / Cross-device | J13: Amazon.co.jp O&O + Open Web (JP) | K13: Display (Static) | L13: Static: Special "Welcome Back" offer or exclusive returning-customer discount. | M13: 01/01/2026 – 12/31/2026 | N13: 302500 | O13: =N13/N14 | P13: 1275 | Q13: =(N13/P13)*1000
A14: TOTALS (9 Line Items | 3 Orders) | N14: =SUM(N5:N13) | O14: =SUM(O5:O13) | P14: =SUMPRODUCT(N5:N13,P5:P13)/SUM(N5:N13) | Q14: =SUM(Q5:Q13)
A16: COLOR KEY: 🚀 Navy = Prospecting (Growth) 🎯 Burgundy = Remarketing (The Closer) 🔁 Forest = Loyalty (LTV) 🟡 Yellow cells = your inputs ⚫ Black text = auto-calculated formula

Sheet ⚙️ Optimization & AMC
A1: ⚙️ OPTIMIZATION & AMAZON MARKETING CLOUD (AMC) GUIDELINES
A2: Active management playbook — review weekly and act on signals
A4: OPTIMIZATION LEVERS
A5: Optimization Lever | B5: Tactic / Action Plan | C5: Check Frequency | D5: Owner
A6: Budget Fluidity | B6: Shift up to 15% of budget from Consideration → Conversion if ROAS exceeds target. Shift from Conversion → Awareness if inventory is running out. | C6: Weekly | D6: Campaign Manager
A7: Frequency Capping | B7: Implement a freq cap of 4x per 7 days on STV to prevent ad fatigue. Lower to 3x if VCR drops below 60%. | C7: Weekly | D7: DSP Trader
A8: AMC Custom Audiences | B8: Use AMC to build: 'Users who saw STV ad + searched brand' → push to Conversion line. 'Viewed PDP 3x but no purchase' → push to BOF retargeting. | C8: Bi-weekly | D8: AMC Analyst
A9: Creative Refresh | B9: Swap BOF REC (Responsive eCommerce) creative every 4 weeks to combat banner blindness. A/B test at least 2 versions simultaneously. | C9: Monthly | D9: Creative Team
A10: Bid Optimisation | B10: Use Dynamic Bids – Up and Down for Conversion line. Fixed bids for Awareness. Review bid landscape every 2 weeks and adjust ±20%. | C10: Bi-weekly | D10: DSP Trader
A11: Audience Suppression | B11: Suppress recent purchasers (last 14 days) from Conversion audiences to avoid waste. Re-add to Retention/Loyalty audience. | C11: Weekly | D11: Campaign Manager
A12: Performance Pacing | B12: Confirm daily delivery is within ±10% of planned daily budget. Escalate if over/under-delivery exceeds 15% for 3 consecutive days. | C12: Daily | D12: Campaign Manager
A15: AMC SQL AUDIENCE TEMPLATES
A16: Audience Name | B16: AMC Logic / SQL Description | C16: Push To | D16: Refresh Cadence
A17: STV Viewer + Brand Searcher | B17: Users exposed to STV impression in last 30 days AND searched brand keyword within same window | C17: Conversion (BOF) | D17: Weekly
A18: PDP Viewer Non-Purchaser | B18: Users who viewed product detail page 2+ times in last 14 days AND have no purchase event | C18: Retargeting (BOF) | D18: Weekly
A19: Cart Abandoner | B19: Users who added to cart in last 7 days AND have no purchase event recorded | C19: Retargeting (BOF) | D19: Daily
A20: Lapsed Buyer – Reactivation | B20: Users who purchased 60–90 days ago AND have no purchase in last 30 days | C20: Retention (Loyalty) | D20: Bi-weekly
A21: High-Value Lookalike | B21: AMC lookalike modelled on top 20% purchasers by LTV; expand reach for TOF | C21: Awareness (TOF) | D21: Monthly

Sheet 💰 Budget Scenarios
A1: 💰 BUDGET SCENARIO PLANNER — Adjust Total Budget to Model Different Allocations (DAIKEN Biomedical JP — ¥ JPY)
A3: TOTAL CAMPAIGN BUDGET INPUT
A4: Total Budget (¥) | B4: 5500000
A6: ALLOCATION SCENARIOS (% of Total Budget)
A7: Order (Goal) | B7: Conservative (Brand Safety) | C7: Balanced (Recommended) | D7: Aggressive (Performance) | E7: Custom %
A8: 🚀 Prospecting (Growth) | B8: 0.45 | C8: 0.39 | D8: 0.25 | E8: 0.39
A9: 🎯 Remarketing (The Closer) | B9: 0.35 | C9: 0.39 | D9: 0.55 | E9: 0.39
A10: 🔁 Loyalty (LTV) | B10: 0.2 | C10: 0.22 | D10: 0.2 | E10: 0.22
A12: CALCULATED BUDGET ALLOCATION ($) — Based on Total Budget in B4
A13: Order (Goal) | B13: Conservative (¥) | C13: Balanced (¥) | D13: Aggressive (¥) | E13: Custom (¥)
A14: 🚀 Prospecting (Growth) | B14: =$B$4*B8 | C14: =$B$4*C8 | D14: =$B$4*D8 | E14: =$B$4*E8
A15: 🎯 Remarketing (The Closer) | B15: =$B$4*B9 | C15: =$B$4*C9 | D15: =$B$4*D9 | E15: =$B$4*E9
A16: 🔁 Loyalty (LTV) | B16: =$B$4*B10 | C16: =$B$4*C10 | D16: =$B$4*D10 | E16: =$B$4*E10
A17: TOTAL | B17: =SUM(B14:B16) | C17: =SUM(C14:C16) | D17: =SUM(D14:D16) | E17: =SUM(E14:E16)

Sheet 📤 DSP Order Bulk
A1: 📤 AMAZON DSP — ORDER BULK UPLOAD | Maps to: DSP Console → Orders → Download → Export Order Settings
A2: 🔵 Blue cells = your inputs | ⚫ Black cells = auto-populated from '📊 Media Plan' tab | 🟡 Yellow = required by Amazon DSP bulk template | Upload this sheet as .xlsx to DSP Console → Orders → Upload
A3: Operation | B3: Order ID | C3: Order Name | D3: Advertiser ID | E3: Start Date | F3: End Date | G3: Budget Type | H3: Budget (¥) | I3: Daily Budget (¥) | J3: Budget Pacing | K3: Frequency Cap | L3: Freq Cap Period | M3: Freq Cap Type | N3: Goal Type | O3: Goal Value | P3: Billing Entity | Q3: Order Status | R3: Notes / Internal Label
A4: ⬇ ROWS 5–8 AUTO-PULL FROM MEDIA PLAN TAB | Fill in columns B, D, P, Q manually | Adjust dates to match your campaign
A5: CREATE | B5: [Leave blank for new] | C5: 🚀 DAIKEN Biomedical | Prospecting (Growth) | D5: [Your DSP Advertiser ID] | E5: 01/01/2026 | F5: 12/31/2026 | G5: budget | H5: =SUM('📊 Media Plan'!N5:N7) | J5: EVEN | K5: 4 | L5: week | M5: impressions | N5: reach | O5: — | P5: [Billing Entity Name] | Q5: active | R5: Media Plan rows: 5–7
A6: CREATE | B6: [Leave blank for new] | C6: 🎯 DAIKEN Biomedical | Remarketing (The Closer) | D6: [Your DSP Advertiser ID] | E6: 01/01/2026 | F6: 12/31/2026 | G6: budget | H6: =SUM('📊 Media Plan'!N8:N10) | J6: EVEN | K6: 7 | L6: week | M6: impressions | N6: roas | O6: 4.0 | P6: [Billing Entity Name] | Q6: active | R6: Media Plan rows: 8–10
A7: CREATE | B7: [Leave blank for new] | C7: 🔁 DAIKEN Biomedical | Loyalty (LTV) | D7: [Your DSP Advertiser ID] | E7: 01/01/2026 | F7: 12/31/2026 | G7: budget | H7: =SUM('📊 Media Plan'!N11:N13) | J7: EVEN | K7: 3 | L7: week | M7: impressions | N7: roas | O7: 3.0 | P7: [Billing Entity Name] | Q7: active | R7: Media Plan rows: 11–13
A10: 📋 HOW TO UPLOAD ORDERS → Step-by-step instructions
A11: Step 1 | B11: Fill in all RED/ORANGE required fields: Advertiser ID (col D) and Billing Entity (col P). These are account-specific.
A12: Step 2 | B12: Verify Order Names (col C) match your naming convention. Edit the formula prefix [Brand] to your brand name.
A13: Step 3 | B13: Confirm Start/End Dates (cols E–F) match your campaign calendar. Budget (col H) auto-pulls from Media Plan tab.
A14: Step 4 | B14: Save this workbook as .xlsx. Then in Amazon DSP Console → Orders tab → click Upload button → select this file.
A15: Step 5 | B15: Amazon will validate the file. Fix any errors flagged in the validation report, then re-upload. Order IDs are assigned on success.
A16: Step 6 | B16: Copy the assigned Order IDs back into col B of this sheet for future UPDATE operations.

Sheet 📤 DSP Line Item Bulk
A1: 📤 AMAZON DSP — LINE ITEM BULK UPLOAD | Maps to: DSP Console → Orders → [Select Order] → Line Items → Download / Upload
A2: One Line Item per row. Each Order (from Order Bulk tab) can contain multiple Line Items. This template creates one Line Item per funnel stage. Add rows to split by format or audience within a stage.
A3: Operation | B3: Line Item ID | C3: Line Item Name | D3: Order ID | E3: Order Name | F3: Line Item Type | G3: Start Date | H3: End Date | I3: Budget Type | J3: Line Item Budget (¥) | K3: Daily Budget (¥) | L3: Bid Strategy | M3: Base Bid (¥) | N3: Supply Source | O3: Audience Segment | P3: Creative Format | Q3: Device Targeting | R3: Geo Targeting | S3: Line Item Status | T3: Notes
A4: CREATE | B4: [After upload] | C4: 🚀 DAIKEN Biomedical | AMC Lookalikes | D4: [Paste Order ID after Order upload] | E4: 🚀 DAIKEN Biomedical | Prospecting (Growth) | F4: video | G4: 01/01/2026 | H4: 12/31/2026 | I4: budget | J4: ='📊 Media Plan'!N5 | L4: fixed | M4: 3300 | N4: AMAZON_OWNED | O4: Lookalike (AMC-Modelled) | P4: STV / OLV | Q4: CTV,MOBILE | R4: Japan | S4: active | T4: Media Plan row 5 | Video / Static: Focus on Japanese wellness heritage and natural supplement quality.
A5: CREATE | B5: [After upload] | C5: 🚀 DAIKEN Biomedical | In-Market Segments | D5: [Paste Order ID after Order upload] | E5: 🚀 DAIKEN Biomedical | Prospecting (Growth) | F5: standard_display | G5: 01/01/2026 | H5: 12/31/2026 | I5: budget | J5: ='📊 Media Plan'!N6 | L5: dynamic_up | M5: 1500 | N5: BOTH | O5: In-Market (Category Intent) | P5: Display + OLV | Q5: ALL | R5: Japan | S5: active | T5: Media Plan row 6 | Static: Highlighting product purity and key supplement benefits.
A6: CREATE | B6: [After upload] | C6: 🚀 DAIKEN Biomedical | Brand Halo / Cross-Brand | D6: [Paste Order ID after Order upload] | E6: 🚀 DAIKEN Biomedical | Prospecting (Growth) | F6: standard_display | G6: 01/01/2026 | H6: 12/31/2026 | I6: budget | J6: ='📊 Media Plan'!N7 | L6: fixed | M6: 1200 | N6: BOTH | O6: Contextual / Category Halo | P6: Display | Q6: ALL | R6: Japan | S6: active | T6: Media Plan row 7 | Static: Promoting DAIKEN as a trusted total wellness brand.
A7: CREATE | B7: [After upload] | C7: 🎯 DAIKEN Biomedical | 7-Day View Remarketing | D7: [Paste Order ID after Order upload] | E7: 🎯 DAIKEN Biomedical | Remarketing (The Closer) | F7: standard_display | G7: 01/01/2026 | H7: 12/31/2026 | I7: budget | J7: ='📊 Media Plan'!N8 | L7: dynamic_up_down | M7: 1200 | N7: AMAZON_OWNED | O7: Remarketing – PDP Viewers (7-day) | P7: REC (Responsive eCommerce) | Q7: ALL | R7: Japan | S7: active | T7: Media Plan row 8 | REC: Dynamic ads showing real-time price & star rating.
A8: CREATE | B8: [After upload] | C8: 🎯 DAIKEN Biomedical | AMC Cart Abandoners | D8: [Paste Order ID after Order upload] | E8: 🎯 DAIKEN Biomedical | Remarketing (The Closer) | F8: standard_display | G8: 01/01/2026 | H8: 12/31/2026 | I8: budget | J8: ='📊 Media Plan'!N9 | L8: dynamic_up_down | M8: 1350 | N8: AMAZON_OWNED | O8: Remarketing – Cart Abandon (AMC) | P8: REC (Responsive eCommerce) | Q8: ALL | R8: Japan | S8: active | T8: Media Plan row 9 | REC: Including a "Limited Time" coupon if available.
A9: CREATE | B9: [After upload] | C9: 🎯 DAIKEN Biomedical | Competitor Conquesting | D9: [Paste Order ID after Order upload] | E9: 🎯 DAIKEN Biomedical | Remarketing (The Closer) | F9: standard_display | G9: 01/01/2026 | H9: 12/31/2026 | I9: budget | J9: ='📊 Media Plan'!N10 | L9: dynamic_up | M9: 1425 | N9: BOTH | O9: Conquesting – Competitor ASIN Viewers | P9: Display (Static) | Q9: ALL | R9: Japan | S9: active | T9: Media Plan row 10 | Static: A "Why Choose DAIKEN?" comparison chart highlighting differentiators.
A10: CREATE | B10: [After upload] | C10: 🔁 DAIKEN Biomedical | Repeat Purchase | D10: [Paste Order ID after Order upload] | E10: 🔁 DAIKEN Biomedical | Loyalty (LTV) | F10: audio | G10: 01/01/2026 | H10: 12/31/2026 | I10: budget | J10: ='📊 Media Plan'!N11 | L10: dynamic_up_down | M10: 1500 | N10: AMAZON_OWNED | O10: Remarketing – Past Buyers (45-day) | P10: Display + Audio | Q10: MOBILE,DESKTOP | R10: Japan | S10: active | T10: Media Plan row 11 | Static: "Time to Refill?" messaging with product + days-since-purchase hook.
A11: CREATE | B11: [After upload] | C11: 🔁 DAIKEN Biomedical | Subscribe & Save (SnS) | D11: [Paste Order ID after Order upload] | E11: 🔁 DAIKEN Biomedical | Loyalty (LTV) | F11: standard_display | G11: 01/01/2026 | H11: 12/31/2026 | I11: budget | J11: ='📊 Media Plan'!N12 | L11: dynamic_up_down | M11: 1350 | N11: AMAZON_OWNED | O11: Remarketing – Frequent Buyers (Non-Sub) | P11: Display (Static) | Q11: ALL | R11: Japan | S11: active | T11: Media Plan row 12 | Static: Highlighting the % discount for SnS + auto-delivery convenience.
A12: CREATE | B12: [After upload] | C12: 🔁 DAIKEN Biomedical | Lapse Prevention | D12: [Paste Order ID after Order upload] | E12: 🔁 DAIKEN Biomedical | Loyalty (LTV) | F12: standard_display | G12: 01/01/2026 | H12: 12/31/2026 | I12: budget | J12: ='📊 Media Plan'!N13 | L12: fixed | M12: 1275 | N12: BOTH | O12: Remarketing – Lapsed (6-month+) | P12: Display (Static) | Q12: ALL | R12: Japan | S12: active | T12: Media Plan row 13 | Static: Special "Welcome Back" offer or exclusive returning-customer discount.
A13: 📋 LINE ITEM UPLOAD SEQUENCE → Must upload Orders FIRST to get Order IDs
A14: Step 1 | B14: Upload the 'DSP Order Bulk' tab first. Amazon will return Order IDs in the confirmation report.
A15: Step 2 | B15: Paste the returned Order IDs into col D of THIS sheet. Match each Line Item to its correct Order by referencing col E (Order Name).
A16: Step 3 | B16: Verify Line Item budgets (col J) sum to the total Order budget. Formulas auto-calculate from Media Plan. Adjust split % in formula if needed.
A17: Step 4 | B17: In DSP Console → Orders → select the Order → Line Items tab → Upload → select this sheet.
A18: Step 5 | B18: After upload, Line Item IDs are returned. Paste into col B for future updates. Associate creatives using the 'DSP Creative Bulk' tab.

Sheet 📤 DSP Creative Bulk
A1: 📤 AMAZON DSP — CREATIVE BULK UPLOAD | Maps to: DSP Console → Creatives → Create Creative → Bulk Upload
A2: Download Amazon's official Creative template from Creatives → Bulk Upload → Download Template. Fill columns A–S from this sheet. Upload .xlsx + zip of image assets together.
A3: Operation | B3: Creative ID | C3: Creative Name | D3: Advertiser ID | E3: Creative Type | F3: Line Item Name(s) | G3: Line Item ID(s) | H3: ASIN | I3: Ad Size | J3: Image File Name | K3: Click-Through URL | L3: Impression Pixel | M3: Click Pixel | N3: Headline | O3: Sub-Headline | P3: CTA Text | Q3: Brand Logo File | R3: Creative Status | S3: Notes
A4: CREATE | B4: [After upload] | C4: PROSP_AMCLookalike_STV_30s_v1 | D4: [Your DSP Advertiser ID] | E4: STV | F4: 🚀 DAIKEN Biomedical | AMC Lookalikes | G4: [LI ID for row 5 — paste after LI upload] | I4: 1920x1080 | J4: prosp_stv_30s_v1.mp4 | K4: https://www.amazon.co.jp/dp/[ASIN] | L4: — | M4: — | N4: DAIKEN Biomedical — Pure. Natural. Trusted. | O4: Premium Japanese Health Supplements | P4: Shop Now | Q4: logo_white.png | R4: active | S4: 30s STV | Prospecting AMC Lookalike | Prime Video
A5: CREATE | B5: [After upload] | C5: PROSP_AMCLookalike_OLV_15s_v1 | D5: [Your DSP Advertiser ID] | E5: OLV | F5: 🚀 DAIKEN Biomedical | AMC Lookalikes | G5: [LI ID for row 5 — paste after LI upload] | I5: 1280x720 | J5: prosp_olv_15s_v1.mp4 | K5: https://www.amazon.co.jp/dp/[ASIN] | L5: — | M5: — | N5: High-Quality Natural Supplements | O5: Nattokinase, Maca, Fish Oil & More | P5: Learn More | Q5: logo_white.png | R5: active | S5: 15s OLV cutdown | Lookalike audience | IMDb + Open Web
A6: CREATE | B6: [After upload] | C6: PROSP_InMarket_Display_300x250_v1 | D6: [Your DSP Advertiser ID] | E6: STANDARD_DISPLAY | F6: 🚀 DAIKEN Biomedical | In-Market Segments | G6: [LI ID for row 6 — paste after LI upload] | I6: 300x250 | J6: inmarket_300x250_v1.jpg | K6: https://www.amazon.co.jp/dp/[ASIN] | L6: — | M6: — | N6: Support Your Health. Naturally. | O6: Premium supplements for daily wellness | P6: Shop Now | Q6: logo_color.png | R6: active | S6: 300x250 | In-Market Heart Health shoppers
A7: CREATE | B7: [After upload] | C7: PROSP_BrandHalo_Display_300x250_v1 | D7: [Your DSP Advertiser ID] | E7: STANDARD_DISPLAY | F7: 🚀 DAIKEN Biomedical | Brand Halo / Cross-Brand | G7: [LI ID for row 7 — paste after LI upload] | I7: 300x250 | J7: brandhalo_300x250_v1.jpg | K7: https://www.amazon.co.jp/dp/[ASIN] | L7: — | M7: — | N7: Total Wellness Starts Here. | O7: DAIKEN — your daily wellness foundation | P7: Discover More | Q7: logo_color.png | R7: active | S7: Brand Halo / Cross-brand | Wellness category shoppers
A8: CREATE | B8: [After upload] | C8: REMARK_7DayView_REC_ASIN1_v1 | D8: [Your DSP Advertiser ID] | E8: REC | F8: 🎯 DAIKEN Biomedical | 7-Day View Remarketing | G8: [LI ID for row 8 — paste after LI upload] | H8: [ASIN] | I8: Responsive | J8: N/A — auto from ASIN | K8: https://www.amazon.co.jp/dp/[ASIN] | L8: — | M8: — | N8: [Auto from listing] | O8: [Auto from listing] | P8: Buy Now | Q8: logo_color.png | R8: active | S8: REC | 7-Day PDP Viewers | Real-time price + stars
A9: CREATE | B9: [After upload] | C9: REMARK_CartAbandon_REC_ASIN1_v1 | D9: [Your DSP Advertiser ID] | E9: REC | F9: 🎯 DAIKEN Biomedical | AMC Cart Abandoners | G9: [LI ID for row 9 — paste after LI upload] | H9: [ASIN] | I9: Responsive | J9: N/A — auto from ASIN | K9: https://www.amazon.co.jp/dp/[ASIN] | L9: — | M9: — | N9: Complete Your Order | O9: Limited-time coupon available | P9: Get It Now | Q9: logo_color.png | R9: active | S9: REC | AMC Cart Abandoners | Coupon urgency variant
A10: CREATE | B10: [After upload] | C10: REMARK_Conquest_Display_300x250_v1 | D10: [Your DSP Advertiser ID] | E10: STANDARD_DISPLAY | F10: 🎯 DAIKEN Biomedical | Competitor Conquesting | G10: [LI ID for row 10 — paste after LI upload] | I10: 300x250 | J10: conquest_300x250_v1.jpg | K10: https://www.amazon.co.jp/dp/[ASIN] | L10: — | M10: — | N10: Why Choose DAIKEN Biomedical? | O10: Natural ingredients. Japanese quality. ★★★★★ | P10: Compare Now | Q10: logo_color.png | R10: active | S10: Competitor conquesting | Why-Choose-Us comparison chart
A11: CREATE | B11: [After upload] | C11: LOYAL_RepeatPurchase_Display_300x250_v1 | D11: [Your DSP Advertiser ID] | E11: STANDARD_DISPLAY | F11: 🔁 DAIKEN Biomedical | Repeat Purchase | G11: [LI ID for row 11 — paste after LI upload] | I11: 300x250 | J11: loyal_refill_300x250_v1.jpg | K11: https://www.amazon.co.jp/dp/[ASIN] | L11: — | M11: — | N11: Time to Refill? 🐟 | O11: Your 45-day supply may be running low. | P11: Reorder Now | Q11: logo_color.png | R11: active | S11: Loyalty | Repeat purchase 45-day trigger
A12: CREATE | B12: [After upload] | C12: LOYAL_SnS_Display_300x250_v1 | D12: [Your DSP Advertiser ID] | E12: STANDARD_DISPLAY | F12: 🔁 DAIKEN Biomedical | Subscribe & Save (SnS) | G12: [LI ID for row 12 — paste after LI upload] | I12: 300x250 | J12: loyal_sns_300x250_v1.jpg | K12: https://www.amazon.co.jp/dp/[ASIN] | L12: — | M12: — | N12: Subscribe & Save 15% | O12: Auto-delivered. Cancel anytime. | P12: Subscribe Now | Q12: logo_color.png | R12: active | S12: Loyalty | SnS conversion | Frequent non-subscriber buyers
A13: CREATE | B13: [After upload] | C13: LOYAL_LapsePrev_Display_300x250_v1 | D13: [Your DSP Advertiser ID] | E13: STANDARD_DISPLAY | F13: 🔁 DAIKEN Biomedical | Lapse Prevention | G13: [LI ID for row 13 — paste after LI upload] | I13: 300x250 | J13: loyal_winback_300x250_v1.jpg | K13: https://www.amazon.co.jp/dp/[ASIN] | L13: — | M13: — | N13: Welcome Back! 🎉 | O13: Exclusive returning customer offer inside. | P13: Claim Offer | Q13: logo_color.png | R13: active | S13: Loyalty | Lapse prevention | 6-month+ non-purchasers
A15: Format | D15: Dimensions | G15: Max File Size | I15: File Types | K15: Duration | M15: Key Notes
A16: STV | D16: 1920×1080 (16:9) | G16: 500 MB | I16: MP4, MOV | K16: 15s / 30s | M16: Non-skippable. No hard-coded CTAs. Audio required. Closed captions recommended.
A17: OLV | D17: 1280×720 or 1920×1080 | G17: 200 MB | I17: MP4, MOV | K17: 6s/15s/30s | M17: Can be skippable. Include logo in first 3 seconds. Ensure message lands without audio.
A18: REC | D18: Responsive (auto) | G18: N/A | I18: Auto (ASIN) | K18: N/A | M18: No image upload required. Amazon pulls from listing. Ensure main image is white-bg, high-res.
A19: Standard Display | D19: 300×250, 728×90, 160×600, 320×50 | G19: 150 KB | I19: JPG, PNG, GIF | K19: N/A | M19: GIF max 30s loop, 3 loops. Always include logo + CTA. Avoid small text.
A20: Audio | D20: Companion: 300×250 | G20: 1 MB img | I20: MP3 / JPG | K20: 15s / 30s | M20: Non-skippable. Companion banner displays during playback. Strong verbal CTA required.

Sheet 🗺️ Upload Sequence & Map
A1: 🗺️ BULK UPLOAD SEQUENCE & FIELD MAPPING GUIDE
A2: Follow this exact sequence. Each step depends on IDs generated in the previous step.
A4: Step | B4: Tab / Action | C4: DSP Console Location | D4: Key Fields | E4: Output | F4: Notes
A5: 1 | B5: MEDIA PLAN (📊 Media Plan tab) | C5: Source of truth | D5: Budget, dates, audience, creative format, CPM | E5: No upload | F5: All other tabs pull from this tab. Fill yellow input cells first.
A6: 2 | B6: ORDER BULK (📤 DSP Order Bulk) | C6: DSP Console → Orders → Upload | D6: Order Name, Budget, Dates, Goal Type | E6: Returns Order IDs | F6: Upload first. Paste Order IDs back into tab col B.
A7: 3 | B7: LINE ITEM BULK (📤 DSP Line Item Bulk) | C7: DSP Console → Orders → [Order] → Line Items → Upload | D7: LI Name, Type, Budget split, Bid, Audience, Format | E7: Returns Line Item IDs | F7: Paste Order IDs into col D. Paste returned LI IDs into col B.
A8: 4 | B8: CREATIVE BULK (📤 DSP Creative Bulk) | C8: DSP Console → Creatives → Bulk Upload | D8: Creative assets + ASIN (REC), Click URL, Headline, CTA | E8: Returns Creative IDs | F8: Paste LI IDs into col G. Upload .xlsx + zip of images together.
A9: 5 | B9: CREATIVE ↔ LINE ITEM Association | C9: DSP Console → Line Items → Edit → Creatives | D9: Map Creative IDs to Line Item IDs | E9: Association confirmed | F9: Can also be done via bulk by including LI IDs in Creative upload.
A10: 6 | B10: QA & LAUNCH | C10: DSP Console → Orders → Review | D10: Check delivery, audience size, bid landscape, creative preview | E10: Campaign goes live | F10: Allow 24–48h for audience population. Check pacing on Day 2.
A13: 🔗 FIELD MAPPING: Media Plan → DSP Bulk Fields
A14: Media Plan Column | B14: Media Plan Tab | C14: → Maps To | D14: DSP Bulk Tab | E14: DSP Bulk Column | F14: Notes
A15: Budget ($) — col M | B15: 📊 Media Plan | C15: → | D15: Budget ($) | E15: 📤 DSP Order Bulk — col H | F15: Formula auto-links. =MP!M5
A16: Budget ($) × split % | B16: 📊 Media Plan | C16: → | D16: Line Item Budget ($) | E16: 📤 DSP Line Item Bulk — col J | F16: Formula: =MP!M5 × split ratio
A17: Flight Dates | B17: 📊 Media Plan | C17: → | D17: Start Date / End Date | E17: 📤 DSP Order Bulk — cols E, F | F17: Manual entry; matches Media Plan
A18: Flight Dates | B18: 📊 Media Plan | C18: → | D18: Start Date / End Date | E18: 📤 DSP Line Item Bulk — cols G,H | F18: Can differ per LI within Order
A19: Funnel Stage | B19: 📊 Media Plan | C19: → | D19: Order Name | E19: 📤 DSP Order Bulk — col C | F19: Used as naming prefix
A20: Creative Format | B20: 📊 Media Plan | C20: → | D20: Creative Type | E20: 📤 DSP Creative Bulk — col E | F20: STV/OLV/REC/DISPLAY/AUDIO
A21: Creative Format | B21: 📊 Media Plan | C21: → | D21: Line Item Type | E21: 📤 DSP Line Item Bulk — col F | F21: video/standard_display/audio
A22: Audience Segment | B22: 📊 Media Plan | C22: → | D22: Audience Segment | E22: 📤 DSP Line Item Bulk — col O | F22: Match to DSP Audience Library name
A23: Geo & Device | B23: 📊 Media Plan | C23: → | D23: Device Targeting | E23: 📤 DSP Line Item Bulk — col Q | F23: CTV / MOBILE / DESKTOP / ALL
A24: Specific Audience Target | B24: 📊 Media Plan | C24: → | D24: Audience Segment | E24: 📤 DSP Line Item Bulk — col O | F24: Use exact DSP audience segment name
A25: Creative Specs (ASIN) | B25: 📊 Media Plan | C25: → | D25: ASIN | E25: 📤 DSP Creative Bulk — col H | F25: REC only — pulls from product listing
A26: Est. CPM ($) — col O | B26: 📊 Media Plan | C26: → | D26: Base Bid ($) | E26: 📤 DSP Line Item Bulk — col M | F26: Starting bid; adjust after launch

Sheet 📖 Glossary
A1: 📖 AMAZON DSP — GLOSSARY OF TERMS & DEFINITIONS
A2: Complete reference guide for Amazon DSP ad formats, audience types, metrics, and strategy terminology
A4: # | B4: Category | C4: Term / Acronym | D4: Definition | E4: Media Plan Relevance
A5: 1 | B5: Ad Format | C5: STV — Streaming TV | D5: Non-skippable video ads (15s or 30s) delivered on connected TV devices via Amazon-owned and -operated properties such as Prime Video, Freevee, and Twitch, as well as third-party streaming apps. Premium, brand-safe inventory with high viewability. | E5: Top-of-Funnel (Awareness). Highest CPM (~$25+) but maximum reach and brand impact. Best for new product launches and brand building.
A6: 2 | B6: Ad Format | C6: OLV — Online Video | D6: Short-form video ads (6s, 15s, 30s) served across desktop and mobile web environments on Amazon-owned sites (IMDb, Twitch) and third-party open web inventory. Can be skippable or non-skippable depending on placement. | E6: Mid-Funnel (Consideration). Lower CPM than STV. Used to re-engage audiences who showed initial interest and drive detail page views (DPVs).
A7: 3 | B7: Ad Format | C7: REC — Responsive eCommerce Creative | D7: Amazon's native ad unit that automatically assembles creative from your product listing data (title, image, star rating, Prime badge, price). Dynamically resizes to fit any IAB display placement. Requires no designer — pulls assets directly from the ASIN. | E7: Bottom-of-Funnel (Conversion). Highest click-to-purchase intent. Refresh every 4 weeks to avoid creative fatigue. A/B test price callout vs. review callout.
A8: 4 | B8: Ad Format | C8: Display Ads | D8: Static or animated banner ads served across Amazon-owned properties and the open web via the DSP. Standard IAB sizes: 300×250 (Medium Rectangle), 728×90 (Leaderboard), 160×600 (Wide Skyscraper), 320×50 (Mobile Banner). Can use custom creative or REC format. | E8: Used across all funnel stages. Awareness = brand imagery. Consideration = product feature callouts. Conversion = price + CTA + rating.
A9: 5 | B9: Ad Format | C9: Audio Ads | D9: 15–30 second non-skippable audio spots delivered on Amazon Music (ad-supported tier) and third-party audio platforms. Includes an optional 'companion banner' (300×250) displayed on the screen while audio plays. | E9: Retention / Loyalty stage. Effective for reaching audiences during 'lean back' moments. Pair companion banner with a Subscribe & Save or coupon CTA.
A10: 6 | B10: Ad Format | C10: IAB Standard Banners | D10: Industry-standard display ad sizes defined by the Interactive Advertising Bureau (IAB). Common sizes: 300×250, 728×90, 160×600, 320×50, 300×600 (Half Page). Used in OLV and display campaigns across open web inventory. | E10: Mid-Funnel and Bottom-of-Funnel. Always build all five IAB sizes to maximize available inventory and reach.
A11: 7 | B11: Audience | C11: Remarketing / Retargeting | D11: Re-engaging users who have previously interacted with your brand or products — e.g., visited your product detail page (PDP), added to cart without purchasing, or viewed your storefront. Uses Amazon's first-party purchase and browsing signals. | E11: Core Bottom-of-Funnel tactic. Segment by recency (7-day, 14-day, 30-day) and depth of engagement (PDP view vs. cart abandon) for best ROI.
A12: 8 | B12: Audience | C12: In-Market Audiences | D12: Pre-built Amazon audience segments consisting of shoppers actively browsing and purchasing in a specific product category. Based on real purchase intent signals from Amazon.com (searches, clicks, purchases in the last 30–90 days). | E12: Mid-Funnel (Consideration). Use to reach category shoppers who haven't yet discovered your brand. Combine with keyword conquesting for maximum impact.
A13: 9 | B13: Audience | C13: Lifestyle Audiences | D13: Audiences defined by long-term shopping patterns and interests (e.g., 'Health & Fitness Enthusiasts', 'Home Improvement DIYers'). Broader than In-Market; based on 12-month purchase history patterns rather than recent intent. | E13: Top-of-Funnel (Awareness). Best for reaching a wide but relevant audience. Combine with lookalike modelling for scale.
A14: 10 | B14: Audience | C14: Lookalike Audiences | D14: Audiences algorithmically modelled to share behavioral and demographic characteristics with your best existing customers (seed audience). Amazon DSP builds lookalikes based on purchase history, browsing behavior, and demographic signals. | E14: Top-of-Funnel expansion. Seed with your top 20% buyers by LTV via AMC. Expect 3–5x the reach of your first-party audience at similar quality.
A15: 11 | B15: Audience | C15: Contextual Targeting | D15: Serving ads on pages or content that are topically relevant to your product, rather than targeting a specific user profile. Example: showing a supplement ad on health-related editorial content on IMDb or third-party health sites. | E15: Awareness and Consideration. Useful when first-party audience pools are small. No cookie or signal dependency — privacy-resilient.
A16: 12 | B16: Audience | C16: Audience Suppression | D16: Excluding a defined audience segment from seeing your ads. Common uses: suppress recent purchasers (avoid wasted spend), suppress existing Subscribe & Save subscribers, suppress high-frequency users showing no conversion signal. | E16: Critical for budget efficiency across all funnel stages. Always suppress last-14-day purchasers from Conversion campaigns and route them to Retention instead.
... A47: 44 | B47: Technical | C47: NTB — New-to-Brand | D47: A customer who has not purchased from your brand on Amazon in the previous 12 months. NTB metrics measure the incremental new customer acquisition driven by advertising, as opposed to re-purchasing existing customers. | E47: Key growth metric for TOF and Conquesting campaigns. Track NTB Purchase Rate in DSP reporting. A healthy DSP campaign should drive 40–60%+ NTB purchases from Awareness and Conquesting lines.
A50: CATEGORY COLOR LEGEND
A51: Ad Format | B51: Audience | C51: Metric / KPI | D51: Strategy | E51: Amazon Tool
A52: Technical
